{
  "run_tag": "v5",
  "cfg_id": 2,
  "src": "ERA5",
  "fold": "B1",
  "best_seed": 566,
  "best_epoch": 58,
  "best_val_mcc": 0.4673897929047886,
  "best_val_acc": 0.7339449541284404,
  "best_val_auc": 0.7255932203389832,
  "best_val_loss": 0.6317029148340225,
  "tp": 43,
  "tn": 37,
  "fp": 13,
  "fn": 16,
  "n_val": 109,
  "val_pos": 59,
  "feature_cols": [
    "temperature_2m_max",
    "temperature_2m_mean",
    "temperature_2m_min",
    "relative_humidity_2m_max",
    "relative_humidity_2m_mean",
    "relative_humidity_2m_min",
    "wind_speed_10m_max",
    "wind_speed_10m_mean",
    "precipitation_sum"
  ],
  "seq_days": [
    21,
    20,
    19,
    18,
    17,
    16,
    15,
    14,
    13,
    12,
    11,
    10,
    9,
    8,
    7,
    6,
    5,
    4,
    3
  ],
  "mean_na_ratio_this_src": 0.0,
  "min_epoch_for_pick": 20
}